fqrng/__init__.py
fqrng/qrng.py
fqrng/cli/__init__.py
fqrng/cli/interface.py
fqrng/core/__init__.py
fqrng/core/nist_validator.c
fqrng/core/nist_validator.cpython-310-x86_64-linux-gnu.so
fqrng/core/qrng_core.c
fqrng/core/qrng_core.cpython-310-x86_64-linux-gnu.so
fqrng/post_processing/__init__.py
fqrng/post_processing/von_neumann.py
fqrng/quantum/__init__.py
fqrng/quantum/beam_splitter.py
fqrng/quantum/ghz_state.py
fqrng/quantum/gpu_manager.py
fq_rng-1.0.0.dist-info/METADATA
fq_rng-1.0.0.dist-info/WHEEL
fq_rng-1.0.0.dist-info/entry_points.txt
fq_rng-1.0.0.dist-info/top_level.txt
fq_rng-1.0.0.dist-info/RECORD
fq_rng-1.0.0.dist-info/licenses/LICENSE
