Metadata-Version: 2.4
Name: FQ-RNG
Version: 1.0.0
Summary: NIST SP 800-22 certified quantum random number generator
Author-email: FQRNG Team <fqrng@example.com>
License: MIT
Project-URL: Homepage, https://github.com/SpecialHopeWaveHereLoop/FQRNGpy
Project-URL: Repository, https://github.com/SpecialHopeWaveHereLoop/FQRNGpy
Project-URL: Documentation, https://github.com/SpecialHopeWaveHereLoop/FQRNGpy#readme
Project-URL: Issues, https://github.com/SpecialHopeWaveHereLoop/FQRNGpy/issues
Project-URL: Changelog, https://github.com/SpecialHopeWaveHereLoop/FQRNGpy/blob/main/CHANGELOG.md
Keywords: quantum,random,rng,cryptography,nist,bell,fractal
Classifier: Development Status :: 4 - Beta
Classifier: Intended Audience :: Developers
Classifier: Intended Audience :: Science/Research
Classifier: License :: OSI Approved :: MIT License
Classifier: Operating System :: OS Independent
Classifier: Programming Language :: Python :: 3
Classifier: Programming Language :: Python :: 3.9
Classifier: Programming Language :: Python :: 3.10
Classifier: Programming Language :: Python :: 3.11
Classifier: Programming Language :: Python :: 3.12
Classifier: Topic :: Scientific/Engineering :: Physics
Classifier: Topic :: Security :: Cryptography
Classifier: Topic :: Software Development :: Libraries :: Python Modules
Requires-Python: >=3.9
License-File: LICENSE
Requires-Dist: numpy>=1.26.0
Requires-Dist: scipy>=1.11.0
Requires-Dist: qutip>=5.0.0
Requires-Dist: cython>=3.0.0
Provides-Extra: dev
Requires-Dist: pytest>=8.0.0; extra == "dev"
Requires-Dist: pytest-cov>=5.0.0; extra == "dev"
Requires-Dist: pytest-xdist>=3.0.0; extra == "dev"
Requires-Dist: safety>=2.3.0; extra == "dev"
Requires-Dist: bandit>=1.7.0; extra == "dev"
Requires-Dist: psutil>=5.9.0; extra == "dev"
Provides-Extra: gpu
Requires-Dist: cupy-cuda11x>=12.0.0; sys_platform == "linux" and extra == "gpu"
Requires-Dist: cupy-cuda12x>=12.0.0; sys_platform == "linux" and extra == "gpu"
Requires-Dist: torch>=2.0.0; extra == "gpu"
Requires-Dist: psutil>=5.9.0; extra == "gpu"
Provides-Extra: quantum
Requires-Dist: qiskit>=1.0.0; extra == "quantum"
Dynamic: license-file
